infernet_ml/__init__.py
infernet_ml/py.typed
infernet_ml/resource/__init__.py
infernet_ml/resource/artifact_manager.py
infernet_ml/resource/repo_id.py
infernet_ml/resource/types.py
infernet_ml/services/__init__.py
infernet_ml/services/ezkl.py
infernet_ml/services/onnx.py
infernet_ml/services/torch.py
infernet_ml/services/types.py
infernet_ml/utils/__init__.py
infernet_ml/utils/css_models.py
infernet_ml/utils/css_mux.py
infernet_ml/utils/diffusion_utils.py
infernet_ml/utils/fileutils.py
infernet_ml/utils/hf_types.py
infernet_ml/utils/model_analyzer.py
infernet_ml/utils/model_manager.py
infernet_ml/utils/onnx_utils.py
infernet_ml/utils/retry.py
infernet_ml/utils/spec.py
infernet_ml/utils/codec/__init__.py
infernet_ml/utils/codec/css.py
infernet_ml/utils/codec/ezkl_codec.py
infernet_ml/utils/codec/vector.py
infernet_ml/utils/specs/__init__.py
infernet_ml/utils/specs/ml_model_id.py
infernet_ml/utils/specs/ml_model_info.py
infernet_ml/utils/specs/ml_type.py
infernet_ml/workflows/__init__.py
infernet_ml/workflows/exceptions.py
infernet_ml/workflows/inference/__init__.py
infernet_ml/workflows/inference/bark_hf_inference_workflow.py
infernet_ml/workflows/inference/base_inference_workflow.py
infernet_ml/workflows/inference/css_inference_workflow.py
infernet_ml/workflows/inference/hf_inference_client_workflow.py
infernet_ml/workflows/inference/onnx_inference_workflow.py
infernet_ml/workflows/inference/stable_diffusion_workflow.py
infernet_ml/workflows/inference/tgi_client_inference_workflow.py
infernet_ml/workflows/inference/torch_inference_workflow.py
infernet_ml/workflows/inference/tts_inference_workflow.py
infernet_ml/zk/__init__.py
infernet_ml/zk/proof_utils.py
infernet_ml/zk/ezkl/__init__.py
infernet_ml/zk/ezkl/ezkl_artifact.py
infernet_ml/zk/ezkl/ezkl_utils.py
infernet_ml/zk/ezkl/types.py
infernet_ml-2.0.0.dist-info/METADATA
infernet_ml-2.0.0.dist-info/WHEEL
infernet_ml-2.0.0.dist-info/RECORD
